image_asserts/__init__.py
image_asserts/files_copy.png
image_asserts/lang_en.png
image_asserts/lang_ru.png
image_asserts/login.png
image_asserts/opened_folder.png
image_asserts/prelogin.png
image_asserts/run_window.png
image_asserts/start_btn.png
image_asserts/start_btn_selected.png
image_logs/.gitignore
image_processing/__init__.py
image_processing/main.py
rdp_manipulations/__init__.py
rdp_manipulations/logger.py
rdp_manipulations/main.py
rdp_manipulations/settings.py
rdp_manipulations-0.3.4.dist-info/LICENSE
rdp_manipulations-0.3.4.dist-info/WHEEL
rdp_manipulations-0.3.4.dist-info/METADATA
rdp_manipulations-0.3.4.dist-info/RECORD
