Metadata-Version: 2.1
Name: rdp-manipulations
Version: 0.3.4
Summary: Image based tool for RDP (Remote Desktop Protocol) manipulations, automations and testing via Python and Apache Guacamole
Home-page: https://github.com/etomarat/rdp-manipulations
License: Apache-2.0
Keywords: rdp,guacamole,automation,image-based,Remote Desktop Protocol
Author: Marat Azizov
Author-email: etomarat@gmail.com
Requires-Python: >=3.10,<4.0
Classifier: License :: OSI Approved :: Apache Software License
Classifier: Programming Language :: Python :: 3
Classifier: Programming Language :: Python :: 3.10
Classifier: Programming Language :: Python :: 3.11
Requires-Dist: environs (>=9.5.0,<10.0.0)
Requires-Dist: loguru (>=0.6.0,<0.7.0)
Requires-Dist: numpy (>=1.23.4,<2.0.0)
Requires-Dist: opencv-python-headless (>=4.6.0.66,<5.0.0.0)
Requires-Dist: playwright (>=1.27.1,<2.0.0)
Project-URL: Documentation, https://github.com/etomarat/rdp-manipulations/blob/main/README.md
Project-URL: Repository, https://github.com/etomarat/rdp-manipulations
